riven_cli/__main__.py
riven_cli/api.py
riven_cli/config.py
riven_cli/http_client.py
riven_cli/utils.py
riven_cli/providers/tmdb.py
riven_cli/tui/app.py
riven_cli/tui/base.py
riven_cli/tui/screens/dashboard.py
riven_cli/tui/screens/details.py
riven_cli/tui/screens/library.py
riven_cli/tui/screens/login.py
riven_cli/tui/screens/logs.py
riven_cli/tui/screens/search.py
riven_cli/tui/screens/settings.py
riven_cli-0.1.6.dist-info/METADATA
riven_cli-0.1.6.dist-info/WHEEL
riven_cli-0.1.6.dist-info/entry_points.txt
riven_cli-0.1.6.dist-info/licenses/LICENSE
riven_cli-0.1.6.dist-info/RECORD
