Metadata-Version: 2.4
Name: riven-cli
Version: 0.1.6
Summary: A powerful TUI for Riven. Manage your library, search content, and monitor your server directly from the terminal.
Project-URL: Homepage, https://github.com/g0ldyy/riven-cli
Project-URL: Issues, https://github.com/g0ldyy/riven-cli/issues
Author: Goldy
License-Expression: MIT
License-File: LICENSE
Classifier: Environment :: Console
Classifier: License :: OSI Approved :: MIT License
Classifier: Operating System :: OS Independent
Classifier: Programming Language :: Python :: 3
Classifier: Topic :: Multimedia
Classifier: Topic :: Utilities
Requires-Python: >=3.13
Requires-Dist: aiohttp>=3.13.2
Requires-Dist: pydantic-settings[toml]>=2.12.0
Requires-Dist: pydantic>=2.12.5
Requires-Dist: pyperclip>=1.11.0
Requires-Dist: readchar>=4.2.1
Requires-Dist: rich>=14.2.0
